E/E.py
E/__init__.py
catlang-0.0.8.dist-info/METADATA
catlang-0.0.8.dist-info/WHEEL
catlang-0.0.8.dist-info/top_level.txt
catlang-0.0.8.dist-info/RECORD
