Metadata-Version: 2.4
Name: catLang
Version: 0.0.8
Summary: catLang: Custom transpiller from catLang code into Python code.
Author: catLang
Classifier: Programming Language :: Python :: 3.13
Classifier: License :: OSI Approved :: MIT License
Requires-Dist: regex>=1.0.0
Dynamic: author
Dynamic: classifier
Dynamic: description
Dynamic: description-content-type
Dynamic: requires-dist
Dynamic: summary
